Lab5/decoder.v
// mips_decode: a decoder for MIPS arithmetic instructions
//
// alu_op       (output) - control signal to be sent to the ALU
// writeenable  (output) - should a new value be captured by the register file
// rd_src       (output) - should the destination register be rd (0) or rt (1)
// alu_src2     (output) - should the 2nd ALU source be a register (0) or an immediate (1)
// except       (output) - set to 1 when we don't recognize an opdcode & funct combination
// control_type (output) - 00 = fallthrough, 01 = branch_target, 10 = jump_target, 11 = jump_register 
// mem_read     (output) - the register value written is coming from the memory
// word_we      (output) - we're writing a word's worth of data
// byte_we      (output) - we're only writing a byte's worth of data
// byte_load    (output) - we're doing a byte load
// slt          (output) - the instruction is an slt
// lui          (output) - the instruction is a lui
// addm         (output) - the instruction is an addm
// opcode        (input) - the opcode field from the instruction
// funct         (input) - the function field from the instruction
// zero          (input) - from the ALU
//

module mips_decode(alu_op, writeenable, rd_src, alu_src2, except, control_type,
                   mem_read, word_we, byte_we, byte_load, slt, lui, addm,
                   opcode, funct, zero);
    output [2:0] alu_op;
    output [1:0] alu_src2;
    output       writeenable, rd_src, except;
    output [1:0] control_type;
    output       mem_read, word_we, byte_we, byte_load, slt, lui, addm;
    input  [5:0] opcode, funct;
    input        zero;

//copy from lab4

    wire add_ = (opcode == `OP_OTHER0) & (funct == `OP0_ADD);    
	wire addi_ = (opcode == `OP_ADDI);       
	wire addu_ = (opcode == `OP_OTHER0) & (funct == `OP0_ADDU);
	wire addiu_ = (opcode == `OP_ADDIU);

	wire sub_ = (opcode == `OP_OTHER0) & (funct == `OP0_SUB);   

	wire and_ = (opcode == `OP_OTHER0) & (funct == `OP0_AND);   
	wire andi_ = (opcode == `OP_ANDI);    

	wire or_ = (opcode == `OP_OTHER0) & (funct == `OP0_OR);  
	wire ori_ = (opcode == `OP_ORI);     

	wire nor_ = (opcode == `OP_OTHER0) & (funct == `OP0_NOR); 

	wire xor_ = (opcode == `OP_OTHER0) & (funct == `OP0_XOR);  
	wire xori_ = (opcode == `OP_XORI);	


//new assignment

    wire bne_ = (opcode == `OP_BNE);
    wire beq_ = (opcode == `OP_BEQ);
    wire j_ = (opcode == `OP_J);
    wire jr_ = (funct == `OP0_JR) & (opcode == `OP_OTHER0);
    wire lui_ = (opcode == `OP_LUI);
    wire slt_ = (opcode == `OP_OTHER0) & (funct == `OP0_SLT);
    wire lw_ = (opcode == `OP_LW);
    wire lbu_ = (opcode == `OP_LBU);
    wire sw_ = (opcode == `OP_SW);
    wire sb_ = (opcode == `OP_SB);
    wire addm_ = (funct == `OP0_ADDM) & (opcode == `OP_OTHER0);



    assign rd_src = (addi_ | addiu_ | andi_ | ori_ | xori_ 
    | lw_ | lbu_ | lui_);

	assign writeenable = (add_ |addu_|addiu_| addi_ | sub_ | and_ | andi_ | or_ | ori_ | xor_ | xori_ | nor_ 
    | lui_ | slt_ | lw_ | lbu_ | addm_ );

    assign except = ~(add_ | addu_| addiu_| addi_ | sub_ | and_ | andi_ | or_ | ori_ | xor_ | xori_ | nor_ 
    | bne_ | beq_ | j_ | jr_ | lui_ | slt_ | lw_ | lbu_ | sw_ | sb_ | addm_);	
    
    assign alu_op[0] = (sub_ | or_ | ori_ | xor_ | xori_ 
    | bne_ | beq_ | slt_ );

	assign alu_op[1] = (sub_ | xor_ | xori_ | nor_ | add_ | addi_ 
    | bne_ | beq_ | slt_ | lw_ | lbu_ | sw_ | sb_ | addm_ );

	assign alu_op[2] = (and_ | andi_ | or_ | ori_ | xor_ | xori_ | nor_ );


	assign alu_src2[1] = (andi_ | ori_ | xori_ );
    assign alu_src2[0] = (addi_ | addiu_ | lbu_ | lw_ | sw_ | sb_);


    assign control_type[0] = ((zero & beq_ ) | (~zero & bne_) | jr_ );
    assign control_type[1] = (j_ | jr_);

    assign mem_read = (lbu_ | lw_ | addm_);

    assign word_we = sw_;
    assign byte_we = sb_;
    assign byte_load = lbu_;
    assign lui = lui_;
    assign slt = slt_;
    assign addm = addm_;



endmodule // mips_decode

Lab5/decoder_tb.v
module decoder_test;
    reg [5:0] opcode, funct;
    reg       zero  = 0;

    initial begin
        $dumpfile("decoder.vcd");
        $dumpvars(0, decoder_test);

        // remember that all your instructions from last week should still work
             opcode = `OP_OTHER0; funct = `OP0_ADD; // see if addition still works
        # 10 opcode = `OP_OTHER0; funct = `OP0_SUB; // see if subtraction still works
        // test all of the others here
        
        // as should all the new instructions from this week
        # 10 opcode = `OP_BEQ; zero = 0; // try a not taken beq
        # 10 opcode = `OP_BEQ; zero = 1; // try a taken beq
        // add more tests here!
        # 10 opcode = `OP_BNE; zero = 0; // try a tanken bne
        # 10 opcode = `OP_BNE; zero = 1; // try a not taken bne
        # 10 opcode = `OP_J;
        # 10 opcode = `OP_OTHER0; funct = `OP0_JR;
        # 10 opcode = `OP_LW;
        # 10 opcode = `OP_LBU;
        # 10 opcode = `OP_SW;
        # 10 opcode = `OP_SB;
        # 10 opcode = `OP_LUI;
        # 10 opcode = `OP_OTHER0; funct = `OP0_SLT;
        # 10 opcode = `OP_OTHER0; funct = `OP0_ADDM;

        # 10 opcode = `OP_ADDI; funct = `OP_OTHER0;
        # 10 opcode = `OP_ADDIU; funct = `OP_OTHER0;
        # 10 opcode = `OP_OTHER0; funct = `OP0_ADDU;

        # 10 opcode = `OP_OTHER0; funct = `OP0_AND;
        # 10 opcode = `OP_OTHER0; funct = `OP0_OR;
        # 10 opcode = `OP_OTHER0; funct = `OP0_NOR;
        # 10 opcode = `OP_OTHER0; funct = `OP0_XOR;
        # 10 opcode = `OP_ANDI;
        # 10 opcode = `OP_ORI;
        # 10 opcode = `OP_XORI;

        # 10 $finish;
    end

    // use gtkwave to test correctness
    wire [2:0] alu_op;
    wire [1:0] alu_src2;
    wire       writeenable, rd_src, except;
    wire [1:0] control_type;
    wire       mem_read, word_we, byte_we, byte_load, slt, lui, addm;
    mips_decode decoder(alu_op, writeenable, rd_src, alu_src2, except, control_type,
                        mem_read, word_we, byte_we, byte_load, slt, lui, addm,
                        opcode, funct, zero);
endmodule // decoder_test

Lab5/decoder.vcd
$date
	Sun Feb 23 19:18:20 2020
$end
$version
	Icarus Verilog
$end
$timescale
	1s
$end
$scope module decoder_test $end
$var wire 1 ! writeenable $end
$var wire 1 " word_we $end
$var wire 1 # slt $end
$var wire 1 $ rd_src $end
$var wire 1 % mem_read $end
$var wire 1 & lui $end
$var wire 1 ' except $end
$var wire 2 ( control_type [1:0] $end
$var wire 1 ) byte_we $end
$var wire 1 * byte_load $end
$var wire 2 + alu_src2 [1:0] $end
$var wire 3 , alu_op [2:0] $end
$var wire 1 - addm $end
$var reg 6 . funct [5:0] $end
$var reg 6 / opcode [5:0] $end
$var reg 1 0 zero $end
$scope module decoder $end
$var wire 1 1 add_ $end
$var wire 1 - addm $end
$var wire 1 2 addm_ $end
$var wire 1 3 addu_ $end
$var wire 1 4 and_ $end
$var wire 1 * byte_load $end
$var wire 1 ) byte_we $end
$var wire 1 ' except $end
$var wire 6 5 funct [5:0] $end
$var wire 1 6 jr_ $end
$var wire 1 & lui $end
$var wire 1 % mem_read $end
$var wire 1 7 nor_ $end
$var wire 6 8 opcode [5:0] $end
$var wire 1 9 or_ $end
$var wire 1 $ rd_src $end
$var wire 1 # slt $end
$var wire 1 : slt_ $end
$var wire 1 ; sub_ $end
$var wire 1 " word_we $end
$var wire 1 ! writeenable $end
$var wire 1 < xor_ $end
$var wire 1 0 zero $end
$var wire 1 = xori_ $end
$var wire 1 > sw_ $end
$var wire 1 ? sb_ $end
$var wire 1 @ ori_ $end
$var wire 1 A lw_ $end
$var wire 1 B lui_ $end
$var wire 1 C lbu_ $end
$var wire 1 D j_ $end
$var wire 2 E control_type [1:0] $end
$var wire 1 F bne_ $end
$var wire 1 G beq_ $end
$var wire 1 H andi_ $end
$var wire 2 I alu_src2 [1:0] $end
$var wire 3 J alu_op [2:0] $end
$var wire 1 K addiu_ $end
$var wire 1 L addi_ $end
$upscope $end
$upscope $end
$enddefinitions $end
#0
$dumpvars
0L
0K
b10 J
b0 I
0H
0G
0F
b0 E
0D
0C
0B
0A
0@
0?
0>
0=
0<
0;
0:
09
b0 8
07
06
b100000 5
04
03
02
11
00
b0 /
b100000 .
0-
b10 ,
b0 +
0*
0)
b0 (
0'
0&
0%
0$
0#
0"
1!
$end
#10
b11 ,
b11 J
01
1;
b100010 .
b100010 5
#20
0!
0;
1G
b100 /
b100 8
#30
b1 (
b1 E
10
#40
0'
b1 (
b1 E
b11 ,
b11 J
00
1F
0G
b101 /
b101 8
#50
b0 (
b0 E
10
#60
b0 ,
b0 J
b10 (
b10 E
0F
1D
b10 /
b10 8
#70
b11 (
b11 E
16
b1000 .
b1000 5
0D
b0 /
b0 8
#80
b10 ,
b10 J
b1 +
b1 I
1!
1$
b0 (
b0 E
1%
06
1A
b100011 /
b100011 8
#90
0A
1*
1C
b100100 /
b100100 8
#100
0%
0!
0$
0*
0C
1"
1>
b101011 /
b101011 8
#110
0"
0>
1)
1?
b101000 /
b101000 8
#120
1!
0'
b0 ,
b0 J
1$
b0 +
b0 I
1&
1B
0)
0?
b1111 /
b1111 8
#130
b11 ,
b11 J
0$
1#
1:
b101010 .
b101010 5
0&
0B
b0 /
b0 8
#140
b10 ,
b10 J
1%
0#
0:
1-
12
b101100 .
b101100 5
#150
1$
b1 +
b1 I
0'
1!
b10 ,
b10 J
0%
0-
02
b0 .
b0 5
1L
b1000 /
b1000 8
#160
b0 ,
b0 J
0L
1K
b1001 /
b1001 8
#170
0'
1!
0$
b0 +
b0 I
13
b100001 .
b100001 5
0K
b0 /
b0 8
#180
b100 ,
b100 J
03
14
b100100 .
b100100 5
#190
b101 ,
b101 J
04
19
b100101 .
b100101 5
#200
b110 ,
b110 J
09
17
b100111 .
b100111 5
#210
0'
1!
b111 ,
b111 J
07
1<
b100110 .
b100110 5
#220
0'
1!
1$
b100 ,
b100 J
b10 +
b10 I
0<
1H
b1100 /
b1100 8
#230
b101 ,
b101 J
0H
1@
b1101 /
b1101 8
#240
b111 ,
b111 J
0@
1=
b1110 /
b1110 8
