Lab2/mux.v
// output is A (when control == 0) or B (when control == 1)
module mux2(out, A, B, control);
    output out;
    input  A, B;
    input  control;
    wire   wA, wB, not_control;
         
    not n1(not_control, control);
    and a1(wA, A, not_control);
    and a2(wB, B, control);
    or  o1(out, wA, wB);
endmodule // mux2

// output is A (when control == 00) or B (when control == 01) or
//           C (when control == 10) or D (when control == 11)
module mux4(out, A, B, C, D, control);
    output      out;
    input       A, B, C, D;
    input [1:0] control;
    wire   out1, out2;

    mux2 oo1(out1, A, B, control[0]);
    mux2 oo2(out2, C, D, control[0]);
    mux2 result(out, out1, out2, control[1]);

endmodule // mux4

Lab2/alu1.v
module full_adder(sum, cout, a, b, cin);
    output sum, cout;
    input  a, b, cin;
    wire   partial_s, partial_c1, partial_c2;

    xor x0(partial_s, a, b);
    xor x1(sum, partial_s, cin);
    and a0(partial_c1, a, b);
    and a1(partial_c2, partial_s, cin);
    or  o1(cout, partial_c1, partial_c2);
endmodule // full_adder

`define ALU_UADD   3'h0
`define ALU_ADD    3'h2
`define ALU_SUB    3'h3
`define ALU_AND    3'h4
`define ALU_OR     3'h5
`define ALU_NOR    3'h6
`define ALU_XOR    3'h7

// 0xx -> arithmetic, 1xx -> logic
module alu1(out, carryout, A, B, carryin, control);
    output      out, carryout;
    input       A, B, carryin;
    input [2:0] control;
    wire logi, arith, bout;
    // add code here!!!
    xor o1(bout, B, control[0]);
    logicunit o2(logi, A, B, control[1:0]);
    full_adder o3(arith, carryout, A, bout, carryin);
    mux2 o4(out, arith, logi, control[2]);

endmodule // alu1

Lab2/logicunit.v
// 00 -> AND, 01 -> OR, 10 -> NOR, 11 -> XOR
module logicunit(out, A, B, control);
    output      out;
    input       A, B;
    input [1:0] control;
    wire r1, r2, r3, r4;

    and o1(r1, A, B);
    or o2(r2, A, B);
    nor o3(r3, A, B);
    xor o4(r4, A, B);

    mux4 result(out, r1, r2, r3, r4, control);

endmodule // logicunit

Lab2/alu1_tb.v
module alu1_test;
    // exhaustively test your 1-bit ALU implementation by adapting mux4_tb.v
        // exhaustively test your logic unit implementation by adapting mux4_tb.v
    // cycle through all combinations of A, B, C, D every 8 time units
    reg A = 0;
    always #1 A = !A;
    reg B = 0;
    always #2 B = !B;
    reg Cin = 0;
    always #4 Cin = !Cin;
     
    reg [2:0] control = 0;
     
    initial begin
        $dumpfile("alu1.vcd");
        $dumpvars(0, alu1_test);

        // control is initially 0
        # 8 control = 1; // wait 8 time units (why 8?) and then set it to 1
        # 8 control = 2; // wait 8 time units and then set it to 2
        # 8 control = 3; // wait 8 time units and then set it to 3
        # 8 control = 4; // wait 8 time units (why 8?) and then set it to 1
        # 8 control = 5; // wait 8 time units and then set it to 2
        # 8 control = 6; // wait 8 time units and then set it to 3
        # 8 control = 7; // wait 8 time units (why 8?) and then set it to 1
        # 8 $finish; // wait 8 time units and then end the simulation
    end

    wire out, Cout;
    alu1 alu_1(out, Cout, A, B, Cin, control);

    // you really should be using gtkwave instead
    /*
    initial begin
        $display("A B C D s o");
        $monitor("%d %d %d %d %d %d (at time %t)", A, B, C, D, control, out, $time);
    end
    */
endmodule

Lab2/alu1.vcd
$date
	Tue Feb  4 19:50:07 2020
$end
$version
	Icarus Verilog
$end
$timescale
	1s
$end
$scope module alu1_test $end
$var wire 1 ! out $end
$var wire 1 " Cout $end
$var reg 1 # A $end
$var reg 1 $ B $end
$var reg 1 % Cin $end
$var reg 3 & control [2:0] $end
$scope module alu_1 $end
$var wire 1 # A $end
$var wire 1 $ B $end
$var wire 1 ' bout $end
$var wire 1 % carryin $end
$var wire 3 ( control [2:0] $end
$var wire 1 ! out $end
$var wire 1 ) logi $end
$var wire 1 " carryout $end
$var wire 1 * arith $end
$scope module o2 $end
$var wire 1 # A $end
$var wire 1 $ B $end
$var wire 2 + control [1:0] $end
$var wire 1 , r1 $end
$var wire 1 - r2 $end
$var wire 1 . r3 $end
$var wire 1 / r4 $end
$var wire 1 ) out $end
$scope module result $end
$var wire 1 , A $end
$var wire 1 - B $end
$var wire 1 . C $end
$var wire 1 / D $end
$var wire 2 0 control [1:0] $end
$var wire 1 1 out2 $end
$var wire 1 2 out1 $end
$var wire 1 ) out $end
$scope module oo1 $end
$var wire 1 , A $end
$var wire 1 - B $end
$var wire 1 3 control $end
$var wire 1 4 not_control $end
$var wire 1 2 out $end
$var wire 1 5 wA $end
$var wire 1 6 wB $end
$upscope $end
$scope module oo2 $end
$var wire 1 . A $end
$var wire 1 / B $end
$var wire 1 7 control $end
$var wire 1 8 not_control $end
$var wire 1 1 out $end
$var wire 1 9 wA $end
$var wire 1 : wB $end
$upscope $end
$scope module result $end
$var wire 1 2 A $end
$var wire 1 1 B $end
$var wire 1 ; control $end
$var wire 1 < not_control $end
$var wire 1 ) out $end
$var wire 1 = wA $end
$var wire 1 > wB $end
$upscope $end
$upscope $end
$upscope $end
$scope module o3 $end
$var wire 1 # a $end
$var wire 1 ' b $end
$var wire 1 % cin $end
$var wire 1 " cout $end
$var wire 1 ? partial_c1 $end
$var wire 1 @ partial_c2 $end
$var wire 1 A partial_s $end
$var wire 1 * sum $end
$upscope $end
$scope module o4 $end
$var wire 1 * A $end
$var wire 1 ) B $end
$var wire 1 B control $end
$var wire 1 C not_control $end
$var wire 1 ! out $end
$var wire 1 D wA $end
$var wire 1 E wB $end
$upscope $end
$upscope $end
$upscope $end
$enddefinitions $end
#0
$dumpvars
0E
0D
1C
0B
0A
0@
0?
0>
0=
1<
0;
0:
19
18
07
06
05
14
03
02
11
b0 0
0/
1.
0-
0,
b0 +
0*
0)
b0 (
0'
b0 &
0%
0$
0#
0"
0!
$end
#1
1!
01
1D
09
1*
1-
0.
1/
1A
1#
#2
1'
0#
1$
#3
1)
1=
0!
12
0D
15
0*
1"
1,
0/
0A
1?
1#
#4
0)
0=
02
11
1!
0"
05
19
1D
0?
0'
0,
0-
1.
1*
0#
0$
1%
#5
0!
01
0D
1"
09
0*
1@
1-
0.
1/
1A
1#
#6
1'
0#
1$
#7
1)
1=
1!
12
1D
15
1*
0@
1,
0/
0A
1?
1#
#8
0)
0=
02
01
1!
04
08
0"
05
09
1D
13
17
1A
0?
0,
0-
1.
1*
b1 +
b1 0
0#
0$
0%
b1 &
b1 (
#9
1)
1=
0!
12
11
0D
16
1:
0*
1"
1-
0.
1/
0A
1?
1#
#10
0"
0?
0'
0#
1$
#11
1!
01
1D
0:
1*
1,
0/
1A
1#
#12
0)
0=
02
0!
06
0D
1"
1'
0,
0-
1.
0*
1@
0#
0$
1%
#13
1)
1=
1!
12
11
1D
16
1:
1*
0@
1-
0.
1/
0A
1?
1#
#14
0"
0?
0'
0#
1$
#15
0!
01
0D
1"
0:
0*
1@
1,
0/
1A
1#
#16
1>
11
1)
19
0=
02
0!
14
18
0<
06
0D
0"
03
07
1;
0A
0,
0-
1.
0*
0@
b10 +
b10 0
0#
0$
0%
b10 &
b10 (
#17
0)
0>
1!
01
1D
09
1*
1-
0.
1/
1A
1#
#18
1'
0#
1$
#19
0!
12
0D
15
0*
1"
1,
0/
0A
1?
1#
#20
1)
1>
02
11
1!
0"
05
19
1D
0?
0'
0,
0-
1.
1*
0#
0$
1%
#21
0)
0>
0!
01
0D
1"
09
0*
1@
1-
0.
1/
1A
1#
#22
1'
0#
1$
#23
1!
12
1D
15
1*
0@
1,
0/
0A
1?
1#
#24
0)
0>
02
01
1!
04
08
0"
05
09
1D
13
17
1A
0?
0,
0-
1.
1*
b11 +
b11 0
0#
0$
0%
b11 &
b11 (
#25
1)
1>
0!
12
11
0D
16
1:
0*
1"
1-
0.
1/
0A
1?
1#
#26
0"
0?
0'
0#
1$
#27
0)
0>
1!
01
1D
0:
1*
1,
0/
1A
1#
#28
02
0!
06
0D
1"
1'
0,
0-
1.
0*
1@
0#
0$
1%
#29
1)
1>
1!
12
11
1D
16
1:
1*
0@
1-
0.
1/
0A
1?
1#
#30
0"
0?
0'
0#
1$
#31
0)
0>
0!
01
0D
1"
0:
0*
1@
1,
0/
1A
1#
#32
11
19
02
14
18
1<
06
0"
03
07
0;
0C
0A
0,
0-
1.
0*
0@
b0 +
b0 0
1B
0#
0$
0%
b100 &
b100 (
#33
01
09
1*
1-
0.
1/
1A
1#
#34
1'
0#
1$
#35
1!
1E
1)
1=
12
15
0*
1"
1,
0/
0A
1?
1#
#36
0!
0E
0)
0=
02
11
0"
05
19
0?
0'
0,
0-
1.
1*
0#
0$
1%
#37
01
1"
09
0*
1@
1-
0.
1/
1A
1#
#38
1'
0#
1$
#39
1!
1E
1)
1=
12
15
1*
0@
1,
0/
0A
1?
1#
#40
0!
0E
0)
0=
02
01
04
08
0"
05
09
13
17
1A
0?
0,
0-
1.
1*
b1 +
b1 0
0#
0$
0%
b101 &
b101 (
#41
1!
1E
1)
1=
12
11
16
1:
0*
1"
1-
0.
1/
0A
1?
1#
#42
0"
0?
0'
0#
1$
#43
01
0:
1*
1,
0/
1A
1#
#44
0!
0E
0)
0=
02
06
1"
1'
0,
0-
1.
0*
1@
0#
0$
1%
#45
1!
1E
1)
1=
12
11
16
1:
1*
0@
1-
0.
1/
0A
1?
1#
#46
0"
0?
0'
0#
1$
#47
01
1"
0:
0*
1@
1,
0/
1A
1#
#48
1!
1>
1E
11
1)
19
0=
02
14
18
0<
06
0"
03
07
1;
0A
0,
0-
1.
0*
0@
b10 +
b10 0
0#
0$
0%
b110 &
b110 (
#49
0!
0E
0)
0>
01
09
1*
1-
0.
1/
1A
1#
#50
1'
0#
1$
#51
12
15
0*
1"
1,
0/
0A
1?
1#
#52
1!
1E
1)
1>
02
11
0"
05
19
0?
0'
0,
0-
1.
1*
0#
0$
1%
#53
0!
0E
0)
0>
01
1"
09
0*
1@
1-
0.
1/
1A
1#
#54
1'
0#
1$
#55
12
15
1*
0@
1,
0/
0A
1?
1#
#56
0!
0E
0)
0>
02
01
04
08
0"
05
09
13
17
1A
0?
0,
0-
1.
1*
b11 +
b11 0
0#
0$
0%
b111 &
b111 (
#57
1!
1E
1)
1>
12
11
16
1:
0*
1"
1-
0.
1/
0A
1?
1#
#58
0"
0?
0'
0#
1$
#59
0!
0E
0)
0>
01
0:
1*
1,
0/
1A
1#
#60
02
06
1"
1'
0,
0-
1.
0*
1@
0#
0$
1%
#61
1!
1E
1)
1>
12
11
16
1:
1*
0@
1-
0.
1/
0A
1?
1#
#62
0"
0?
0'
0#
1$
#63
0!
0E
0)
0>
01
1"
0:
0*
1@
1,
0/
1A
1#
#64
02
06
0"
1'
0,
0-
1.
1*
0@
0#
0$
0%
